pywisp_emibcn/__init__.py
pywisp_emibcn/aircontrol.py
pywisp_emibcn/interactive.py
pywisp_emibcn/mikrotik.py
pywisp_emibcn/pywisp.py
pywisp_emibcn/sshdevice.py
pywisp_emibcn/wisp.py
pywisp_emibcn-0.0.11.data/scripts/pywisp
pywisp_emibcn-0.0.11.dist-info/LICENSE
pywisp_emibcn-0.0.11.dist-info/METADATA
pywisp_emibcn-0.0.11.dist-info/WHEEL
pywisp_emibcn-0.0.11.dist-info/top_level.txt
pywisp_emibcn-0.0.11.dist-info/RECORD
