Metadata-Version: 2.1
Name: pywisp-emibcn
Version: 0.0.11
Summary: Access AirControl2, AirOS & Mikrotik
Home-page: https://github.com/emibcn/pywisp
Author: https://github.com/emibcn
Author-email: emibcn.github@gmail.com
License: GPLv3
Project-URL: Bug Tracker, https://github.com/emibcn/pywisp/issues
Platform: any
Classifier: Programming Language :: Python :: 3
Classifier: License :: OSI Approved :: GNU General Public License v3 or later (GPLv3+)
Classifier: Operating System :: OS Independent
Classifier: Intended Audience :: Developers
Classifier: Environment :: Console
Classifier: Environment :: Web Environment
Classifier: Environment :: Other Environment
License-File: LICENSE
Requires-Dist: requests
Requires-Dist: paramiko
Requires-Dist: termcolor
Requires-Dist: argparse
Requires-Dist: configparser
